TEMD/__init__.py
TEMD/ast_checker.py
TEMD/decoder.py
TEMD/temd.py
TEMD/models/ast_error_model.joblib
TEMD/models/runtime_error_model.joblib
TEMD-0.1.1.dist-info/LICENSE
TEMD-0.1.1.dist-info/METADATA
TEMD-0.1.1.dist-info/WHEEL
TEMD-0.1.1.dist-info/top_level.txt
TEMD-0.1.1.dist-info/RECORD
