Metadata-Version: 2.1
Name: TEMD
Version: 0.1.1
Summary: Enhanced Error Message Decoder for Python
Home-page: https://raw.githubusercontent.com/Sujaykharat/python-error-dataset/main/errors_dataset.json
Author: EMD Team
Author-email: adityakhair45@gmail.com
Classifier: Programming Language :: Python :: 3
Classifier: License :: OSI Approved :: MIT License
Classifier: Operating System :: OS Independent
Requires-Python: >=3.6
License-File: LICENSE
Requires-Dist: scikit-learn>=0.24.0
Requires-Dist: requests>=2.25.0
Requires-Dist: joblib>=0.17.0
